matid-2.1.5.dist-info/RECORD
matid-2.1.5.dist-info/LICENSE
matid-2.1.5.dist-info/WHEEL
matid-2.1.5.dist-info/top_level.txt
matid-2.1.5.dist-info/METADATA
matid/ext.cpython-310-darwin.so
matid/__init__.py
matid/classification/classifications.py
matid/classification/classifier.py
matid/classification/__init__.py
matid/core/system.py
matid/core/distances.py
matid/core/__init__.py
matid/core/lattice.py
matid/core/periodicfinder.py
matid/core/linkedunits.py
matid/ext/geometry.cpp
matid/ext/celllist.cpp
matid/ext/ext.cpp
matid/ext/celllist.h
matid/ext/geometry.h
matid/clustering/__init__.py
matid/clustering/sbc.py
matid/clustering/cluster.py
matid/utils/__init__.py
matid/utils/segfault_protect.py
matid/utils/surfacegenerator.py
matid/utils/exceptions.py
matid/utils/symmetry_info_generation/generate_symmetry_info.py
matid/utils/symmetry_info_generation/query_space_group_info.py
matid/utils/symmetry_info_generation/query_conventional_transform_info.py
matid/utils/symmetry_info_generation/query_continuous_translations.py
matid/utils/symmetry_info_generation/query_wyckoff_sets.py
matid/utils/symmetry_info_generation/query_normalizers.py
matid/symmetry/__init__.py
matid/symmetry/wyckoffset.py
matid/symmetry/symmetryanalyzer.py
matid/geometry/__init__.py
matid/geometry/geometry.py
matid/data/element_data.py
matid/data/constants.py
matid/data/__init__.py
matid/data/symmetry_data.py
matid/data/alphabet_data.py
