Metadata-Version: 2.1
Name: matid
Version: 2.1.5
Summary: MatID is a Python package for identifying and analyzing atomistic systems based on their structure.
Author: Lauri Himanen
License: Apache License
Project-URL: Documentation, https://nomad-coe.github.io/matid/
Project-URL: Source, https://github.com/nomad-coe/matid
Keywords: atoms,structure,materials,science,crystal,symmetry
Classifier: Development Status :: 5 - Production/Stable
Classifier: Intended Audience :: Developers
Classifier: Topic :: Scientific/Engineering :: Physics
Classifier: License :: OSI Approved :: Apache Software License
Classifier: Programming Language :: Python
Classifier: Programming Language :: Python :: 3
Classifier: Programming Language :: Python :: 3 :: Only
Classifier: Programming Language :: Python :: 3.8
Classifier: Programming Language :: Python :: 3.9
Classifier: Programming Language :: Python :: 3.10
Classifier: Programming Language :: Python :: 3.11
Classifier: Programming Language :: Python :: 3.12
Requires-Python: >=3.8
License-File: LICENSE
Requires-Dist: numpy
Requires-Dist: ase
Requires-Dist: spglib>=2.0.0
Requires-Dist: scikit-learn
Requires-Dist: networkx>=2.4
Provides-Extra: dev
Requires-Dist: coverage; extra == "dev"
Requires-Dist: pytest; extra == "dev"
Requires-Dist: ruff; extra == "dev"
Requires-Dist: pydoc-markdown; extra == "dev"
Requires-Dist: genbadge[coverage]; extra == "dev"
